diec/__init__.py
diec/cli.py
diec/decrypt.py
diec/encrypt.py
diec-3.2.dist-info/LICENSE
diec-3.2.dist-info/METADATA
diec-3.2.dist-info/WHEEL
diec-3.2.dist-info/dependency_links.txt
diec-3.2.dist-info/entry_points.txt
diec-3.2.dist-info/top_level.txt
diec-3.2.dist-info/RECORD
