Metadata-Version: 2.1
Name: diec
Version: 3.2
Summary: A tool that encodes text and provides a key for decoding!
Home-page: https://github.com/VelisCore/diec
Download-URL: https://github.com/VelisCore/diec/archive/refs/tags/v3.2.tar.gz
Author: VelisCOre
Author-email: velis.help@web.de
License: MIT
Keywords: diec,encoding,decoding,Velis
Classifier: Development Status :: 5 - Production/Stable
Classifier: Intended Audience :: Developers
Classifier: Topic :: Software Development :: Libraries
Classifier: License :: OSI Approved :: MIT License
Classifier: Programming Language :: Python :: 3.9
Requires-Python: >=3.9
License-File: LICENSE
Requires-Dist: binaryconvert
Requires-Dist: argon2
Requires-Dist: cryptography
Requires-Dist: click
